{"rates": {"MZN": 1, "AED": 0.05746, "AFN": 1.3195, "ALL": 1.4723, "AMD": 6.0492, "ANG": 0.02801, "AOA": 12.9029, "ARS": 4.4569, "AUD": 0.024, "AWG": 0.02801, "AZN": 0.02662, "BAM": 0.02788, "BBD": 0.03129, "BDT": 1.712, "BGN": 0.02788, "BHD": 0.005883, "BIF": 44.4818, "BMD": 0.01565, "BND": 0.02112, "BOB": 0.1085, "BRL": 0.07662, "BSD": 0.01565, "BTN": 1.2964, "BWP": 0.2121, "BYN": 0.04902, "BZD": 0.03129, "CAD": 0.02103, "CDF": 36.1087, "CHF": 0.01372, "CLP": 13.493, "CNY": 0.1134, "COP": 63.5631, "CRC": 8.4143, "CUP": 0.3755, "CVE": 1.5721, "CZK": 0.3444, "DJF": 2.7807, "DKK": 0.1064, "DOP": 0.8876, "DZD": 2.1265, "EGP": 0.4834, "ERN": 0.2347, "ETB": 0.8572, "EUR": 0.01426, "FJD": 0.03514, "FKP": 0.0123, "FOK": 0.1064, "GBP": 0.0123, "GEL": 0.04104, "GGP": 0.0123, "GHS": 0.1762, "GIP": 0.0123, "GMD": 0.9841, "GNF": 134.1078, "GTQ": 0.1232, "GYD": 3.2777, "HKD": 0.1223, "HNL": 0.3852, "HRK": 0.1074, "HTG": 2.1386, "HUF": 5.4841, "IDR": 240.85, "ILS": 0.05844, "IMP": 0.0123, "INR": 1.2964, "IQD": 20.5612, "IRR": 674.2409, "ISK": 2.0585, "JEP": 0.0123, "JMD": 2.418, "JOD": 0.01109, "JPY": 2.261, "KES": 2.2532, "KGS": 1.3762, "KHR": 64.9159, "KID": 0.024, "KMF": 7.014, "KRW": 20.6738, "KWD": 0.004814, "KYD": 0.01304, "KZT": 6.9749, "LAK": 302.2099, "LBP": 234.6966, "LKR": 5.0029, "LRD": 2.9187, "LSL": 0.2962, "LYD": 0.07507, "MAD": 0.1537, "MDL": 0.2763, "MGA": 69.7034, "MKD": 0.8777, "MMK": 32.934, "MNT": 54.1282, "MOP": 0.126, "MRU": 0.5932, "MUR": 0.7102, "MVR": 0.2421, "MWK": 17.0693, "MXN": 0.2667, "MYR": 0.07167, "NAD": 0.2962, "NGN": 11.8015, "NIO": 0.573, "NOK": 0.1624, "NPR": 2.0742, "NZD": 0.02603, "OMR": 0.006016, "PAB": 0.01565, "PEN": 0.05794, "PGK": 0.05614, "PHP": 0.8819, "PKR": 4.5026, "PLN": 0.0634, "PYG": 114.2362, "QAR": 0.05695, "RON": 0.07048, "RSD": 1.6713, "RUB": 1.5411, "RWF": 19.1281, "SAR": 0.05867, "SBD": 0.1329, "SCR": 0.2082, "SDG": 8.6918, "SEK": 0.1685, "SGD": 0.02112, "SHP": 0.0123, "SLE": 0.3442, "SLL": 344.1734, "SOS": 8.916, "SRD": 0.5968, "SSP": 15.7746, "STN": 0.3493, "SYP": 202.4222, "SZL": 0.2962, "THB": 0.5489, "TJS": 0.1718, "TMT": 0.05476, "TND": 0.04818, "TOP": 0.03689, "TRY": 0.4236, "TTD": 0.1061, "TVD": 0.024, "TWD": 0.4973, "TZS": 39.1954, "UAH": 0.5784, "UGX": 57.9677, "USD": 0.01565, "UYU": 0.5984, "UZS": 184.1083, "VES": 0.4933, "VND": 370.9453, "VUV": 1.8912, "WST": 0.0429, "XAF": 9.352, "XCD": 0.04225, "XDR": 0.01169, "XOF": 9.352, "XPF": 1.7013, "YER": 3.9192, "ZAR": 0.2962, "ZMW": 0.2977, "ZWL": 74.8821}, "base": "MZN"}