{"rates": {"SRD": 1, "AED": 0.0963, "AFN": 2.2109, "ALL": 2.4668, "AMD": 10.1352, "ANG": 0.04694, "AOA": 21.8406, "ARS": 7.4674, "AUD": 0.04009, "AWG": 0.04694, "AZN": 0.0446, "BAM": 0.04671, "BBD": 0.05245, "BDT": 2.8684, "BGN": 0.04671, "BHD": 0.00986, "BIF": 74.5281, "BMD": 0.02622, "BND": 0.03534, "BOB": 0.1818, "BRL": 0.1286, "BSD": 0.02622, "BTN": 2.1733, "BWP": 0.3549, "BYN": 0.08221, "BZD": 0.05245, "CAD": 0.03519, "CDF": 65.0807, "CHF": 0.023, "CLP": 22.591, "CNY": 0.1892, "COP": 106.4988, "CRC": 14.098, "CUP": 0.6293, "CVE": 2.6335, "CZK": 0.5798, "DJF": 4.6604, "DKK": 0.1782, "DOP": 1.4872, "DZD": 3.5629, "EGP": 0.8094, "ERN": 0.3933, "ETB": 1.4468, "EUR": 0.02388, "FJD": 0.0587, "FKP": 0.02063, "FOK": 0.1782, "GBP": 0.02063, "GEL": 0.06876, "GGP": 0.02063, "GHS": 0.2932, "GIP": 0.02063, "GMD": 1.6488, "GNF": 224.6949, "GTQ": 0.2063, "GYD": 5.4917, "HKD": 0.2051, "HNL": 0.6454, "HRK": 0.18, "HTG": 3.5832, "HUF": 9.2915, "IDR": 403.25, "ILS": 0.09787, "IMP": 0.02063, "INR": 2.1733, "IQD": 34.4499, "IRR": 1129.6513, "ISK": 3.4466, "JEP": 0.02063, "JMD": 4.0514, "JOD": 0.01859, "JPY": 3.7773, "KES": 3.7636, "KGS": 2.3058, "KHR": 108.7648, "KID": 0.04009, "KMF": 11.75, "KRW": 34.6137, "KWD": 0.008066, "KYD": 0.02185, "KZT": 11.6863, "LAK": 506.3475, "LBP": 393.3435, "LKR": 8.3807, "LRD": 4.8903, "LSL": 0.4976, "LYD": 0.1258, "MAD": 0.2561, "MDL": 0.4629, "MGA": 116.7863, "MKD": 1.4721, "MMK": 55.18, "MNT": 90.6905, "MOP": 0.2113, "MRU": 0.9938, "MUR": 1.1862, "MVR": 0.4056, "MWK": 28.4334, "MXN": 0.4476, "MYR": 0.12, "MZN": 1.6755, "NAD": 0.4976, "NGN": 20.1029, "NIO": 0.9601, "NOK": 0.2676, "NPR": 3.4772, "NZD": 0.04328, "OMR": 0.01008, "PAB": 0.02622, "PEN": 0.09707, "PGK": 0.09407, "PHP": 1.4766, "PKR": 7.5439, "PLN": 0.1066, "PYG": 191.3993, "QAR": 0.09545, "RON": 0.1181, "RSD": 2.8002, "RUB": 2.5433, "RWF": 30.9136, "SAR": 0.09834, "SBD": 0.2226, "SCR": 0.3489, "SDG": 13.454, "SEK": 0.2799, "SGD": 0.03534, "SHP": 0.02063, "SLE": 0.5772, "SLL": 577.2358, "SOS": 14.9385, "SSP": 26.2057, "STN": 0.5851, "SYP": 339.1565, "SZL": 0.4976, "THB": 0.921, "TJS": 0.2881, "TMT": 0.09184, "TND": 0.08094, "TOP": 0.06186, "TRY": 0.7092, "TTD": 0.1779, "TVD": 0.04009, "TWD": 0.8331, "TZS": 65.6403, "UAH": 0.9684, "UGX": 95.9487, "USD": 0.02622, "UYU": 1.0027, "UZS": 308.4671, "VES": 0.8267, "VND": 621.5107, "VUV": 3.1718, "WST": 0.07188, "XAF": 15.6666, "XCD": 0.0708, "XDR": 0.0196, "XOF": 15.6666, "XPF": 2.8501, "YER": 6.5666, "ZAR": 0.4976, "ZMW": 0.4973, "ZWL": 125.5896}, "base": "SRD"}